solarforecastarbiter/__init__.py
solarforecastarbiter/_version.py
solarforecastarbiter/cli.py
solarforecastarbiter/conftest.py
solarforecastarbiter/datamodel.py
solarforecastarbiter/pvmodel.py
solarforecastarbiter/utils.py
solarforecastarbiter/io/__init__.py
solarforecastarbiter/io/api.py
solarforecastarbiter/io/nwp.py
solarforecastarbiter/io/reference_aggregates.py
solarforecastarbiter/io/utils.py
solarforecastarbiter/io/fetch/__init__.py
solarforecastarbiter/io/fetch/arm.py
solarforecastarbiter/io/fetch/bsrn.py
solarforecastarbiter/io/fetch/eia.py
solarforecastarbiter/io/fetch/nwp.py
solarforecastarbiter/io/fetch/pvdaq.py
solarforecastarbiter/io/fetch/rtc.py
solarforecastarbiter/io/fetch/tests/test_arm.py
solarforecastarbiter/io/fetch/tests/test_bsrn.py
solarforecastarbiter/io/fetch/tests/test_eia.py
solarforecastarbiter/io/fetch/tests/test_fetch_nwp.py
solarforecastarbiter/io/fetch/tests/test_init.py
solarforecastarbiter/io/fetch/tests/test_pvdaq.py
solarforecastarbiter/io/fetch/tests/test_rtc.py
solarforecastarbiter/io/fetch/tests/data/bsrn-lr0100-pay0616.dat
solarforecastarbiter/io/fetch/tests/data/bsrn-pay0616.dat.gz
solarforecastarbiter/io/fetch/tests/data/doe_rtc_system.json
solarforecastarbiter/io/fetch/tests/data/doe_rtc_weather.json
solarforecastarbiter/io/fetch/tests/data/eia_caiso.json
solarforecastarbiter/io/fetch/tests/data/eia_caiso_bad.json
solarforecastarbiter/io/fetch/tests/data/gpmetE15.b1.20180130.000000.cdf
solarforecastarbiter/io/fetch/tests/data/gpmetE15.b1.20180130.200000.cdf
solarforecastarbiter/io/fetch/tests/data/pvdaq_2019_data.csv
solarforecastarbiter/io/fetch/tests/data/pvdaq_2020_data.csv
solarforecastarbiter/io/fetch/tests/data/pvdaq_metadata.json
solarforecastarbiter/io/fetch/tests/data/sgpmetE13.b1.20190122.000000.cdf
solarforecastarbiter/io/fetch/tests/data/sgpqcrad1longC1.c1.20190122.000000.cdf
solarforecastarbiter/io/fetch/tests/data/grib/rap.t00z.awp130pgrbf00.grib2
solarforecastarbiter-1.0.13.dist-info/LICENSE
solarforecastarbiter-1.0.13.dist-info/METADATA
solarforecastarbiter-1.0.13.dist-info/WHEEL
solarforecastarbiter-1.0.13.dist-info/entry_points.txt
solarforecastarbiter-1.0.13.dist-info/top_level.txt
solarforecastarbiter-1.0.13.dist-info/RECORD
